riboloco/__init__.py
riboloco/__main__.py
riboloco/convert_gff.py
riboloco/convert_gtf.py
riboloco/find_orfs.py
riboloco/shared_riboloco_functions.py
riboloco-0.3.10.dist-info/LICENSE
riboloco-0.3.10.dist-info/METADATA
riboloco-0.3.10.dist-info/WHEEL
riboloco-0.3.10.dist-info/entry_points.txt
riboloco-0.3.10.dist-info/top_level.txt
riboloco-0.3.10.dist-info/RECORD
