Metadata-Version: 2.1
Name: riboloco
Version: 0.3.10
Summary: Riboseq analysis
Home-page: https://github.com/Delayed-Gitification/riboloco.git
Author: Oscar Wilkins
Author-email: oscar.wilkins@crick.ac.uk
License: MIT
Platform: UNKNOWN
Classifier: License :: OSI Approved :: MIT License
Classifier: Programming Language :: Python :: 3
Classifier: Programming Language :: Python :: 3.7
Requires-Dist: pandas
Requires-Dist: scipy
Requires-Dist: pysam
Requires-Dist: matplotlib
Requires-Dist: seaborn
Requires-Dist: gffutils
Requires-Dist: sklearn
